mcp_network_jcd/__init__.py
mcp_network_jcd/py.typed
mcp_network_jcd/server.py
mcp_network_jcd/models/__init__.py
mcp_network_jcd/models/cisco.py
mcp_network_jcd/models/paloalto.py
mcp_network_jcd/tools/__init__.py
mcp_network_jcd/tools/cisco.py
mcp_network_jcd/tools/paloalto.py
mcp_network_jcd-0.2.0.dist-info/METADATA
mcp_network_jcd-0.2.0.dist-info/WHEEL
mcp_network_jcd-0.2.0.dist-info/entry_points.txt
mcp_network_jcd-0.2.0.dist-info/licenses/LICENSE
mcp_network_jcd-0.2.0.dist-info/RECORD
