Metadata-Version: 2.4
Name: mcp-network-jcd
Version: 0.2.0
Summary: MCP server for network device queries via SSH (Palo Alto firewalls, Cisco IOS)
Author-email: JCDecaux <build-infra@jcdecaux.com>
License: MIT License
License-File: LICENSE
Keywords: cisco,firewall,mcp,model-context-protocol,network,paloalto,ssh,switch
Classifier: Development Status :: 3 - Alpha
Classifier: Intended Audience :: Developers
Classifier: Intended Audience :: System Administrators
Classifier: License :: OSI Approved :: MIT License
Classifier: Programming Language :: Python :: 3
Classifier: Programming Language :: Python :: 3.12
Classifier: Topic :: System :: Networking
Classifier: Topic :: System :: Networking :: Firewalls
Classifier: Topic :: System :: Systems Administration
Requires-Python: >=3.12
Requires-Dist: mcp>=1.0.0
Requires-Dist: netmiko>=4.0.0
Requires-Dist: pydantic>=2.0.0
Provides-Extra: dev
Requires-Dist: pytest-asyncio>=0.23.0; extra == 'dev'
Requires-Dist: pytest-cov>=4.0.0; extra == 'dev'
Requires-Dist: pytest-mock>=3.12.0; extra == 'dev'
Requires-Dist: pytest>=8.0.0; extra == 'dev'
Requires-Dist: ruff>=0.1.0; extra == 'dev'
